ml4h/DatabaseClient.py
ml4h/TensorMap.py
ml4h/__init__.py
ml4h/arguments.py
ml4h/data_descriptions.py
ml4h/defines.py
ml4h/explorations.py
ml4h/hypertuning.py
ml4h/logger.py
ml4h/make_tensor_maps_for_partners_ecg_labels.py
ml4h/metrics.py
ml4h/normalizer.py
ml4h/optimizers.py
ml4h/plots.py
ml4h/recipes.py
ml4h/runtime_data_defines.py
ml4h/tensor_generators.py
ml4h/test_utils.py
ml4h/ml4ht_integration/__init__.py
ml4h/ml4ht_integration/tensor_generator.py
ml4h/ml4ht_integration/tensor_map.py
ml4h/models/Block.py
ml4h/models/__init__.py
ml4h/models/basic_blocks.py
ml4h/models/conv_blocks.py
ml4h/models/diffusion_blocks.py
ml4h/models/inspect.py
ml4h/models/layer_wrappers.py
ml4h/models/legacy_models.py
ml4h/models/merge_blocks.py
ml4h/models/model_factory.py
ml4h/models/perceiver_blocks.py
ml4h/models/pretrained_blocks.py
ml4h/models/train.py
ml4h/models/train_diffusion.py
ml4h/models/transformer_blocks.py
ml4h/models/transformer_blocks_embedding.py
ml4h/tensorize/__init__.py
ml4h/tensorize/merge_hd5s.py
ml4h/tensorize/tensor_writer_mgb.py
ml4h/tensorize/tensor_writer_ukbb.py
ml4h/tensorize/tensorize_dataflow.py
ml4h/tensorize/dataflow/__init__.py
ml4h/tensorize/dataflow/bigquery_ukb_queries.py
ml4h/tensormap/__init__.py
ml4h/tensormap/celeba.py
ml4h/tensormap/gatk.py
ml4h/tensormap/general.py
ml4h/tensormap/mnist.py
ml4h/tensormap/tensor_map_maker.py
ml4h/tensormap/text.py
ml4h/tensormap/mgb/__init__.py
ml4h/tensormap/mgb/dynamic.py
ml4h/tensormap/mgb/ecg.py
ml4h/tensormap/mgb/xdl.py
ml4h/tensormap/ukb/__init__.py
ml4h/tensormap/ukb/categorical.py
ml4h/tensormap/ukb/continuous.py
ml4h/tensormap/ukb/demographics.py
ml4h/tensormap/ukb/disease.py
ml4h/tensormap/ukb/dxa.py
ml4h/tensormap/ukb/ecg.py
ml4h/tensormap/ukb/embedding.py
ml4h/tensormap/ukb/genetics.py
ml4h/tensormap/ukb/mri.py
ml4h/tensormap/ukb/mri_brain.py
ml4h/tensormap/ukb/mri_ecg.py
ml4h/tensormap/ukb/mri_vtk.py
ml4h/tensormap/ukb/survival.py
ml4h/visualization_tools/__init__.py
ml4h-0.1.1.dist-info/licenses/LICENSE.txt
ml4h-0.1.1.dist-info/licenses/NOTICE.txt
ml4h-0.1.1.dist-info/METADATA
ml4h-0.1.1.dist-info/WHEEL
ml4h-0.1.1.dist-info/top_level.txt
ml4h-0.1.1.dist-info/RECORD
