Metadata-Version: 2.4
Name: ml4h
Version: 0.1.1
Summary: Machine Learning for Health python package
Home-page: https://github.com/broadinstitute/ml4h
Requires-Python: >=3.6
License-File: LICENSE.txt
License-File: NOTICE.txt
Requires-Dist: PyYAML
Requires-Dist: pydot
Requires-Dist: nibabel==4.0.2
Requires-Dist: pydicom==1.2.2
Requires-Dist: seaborn
Requires-Dist: scikit-image
Requires-Dist: peakutils
Requires-Dist: biosppy
Requires-Dist: imageio
Requires-Dist: ipywidgets>=7.5.1
Requires-Dist: bokeh
Requires-Dist: pillow
Requires-Dist: notebook
Requires-Dist: pytest
Requires-Dist: pytest-xdist
Requires-Dist: pysam
Requires-Dist: tensorflow==2.19.0
Requires-Dist: tensorflow_hub
Requires-Dist: tensorflow_probability
Requires-Dist: tensorflow-text
Requires-Dist: tf-models-official
Requires-Dist: keras-tuner
Requires-Dist: numcodecs
Requires-Dist: beautifulsoup4
Requires-Dist: lxml
Requires-Dist: xmltodict
Requires-Dist: google-cloud-bigquery
Requires-Dist: google-cloud-bigquery-storage
Requires-Dist: pandas_gbq
Requires-Dist: pyarrow
Requires-Dist: altair
Requires-Dist: facets-overview
Requires-Dist: plotnine
Requires-Dist: vega
Requires-Dist: ipycanvas>=0.7.0
Requires-Dist: ipyannotations>=0.2.1
Requires-Dist: torch==2.2.2
Requires-Dist: opencv-python
Requires-Dist: blosc
Requires-Dist: boto3
Requires-Dist: ml4ht==0.0.10
Requires-Dist: google-cloud-storage
Requires-Dist: umap-learn[plot]
Requires-Dist: neurite
Requires-Dist: voxelmorph
Requires-Dist: pystrum
Requires-Dist: av
Requires-Dist: lmdb
Dynamic: description
Dynamic: description-content-type
Dynamic: home-page
Dynamic: license-file
Dynamic: requires-dist
Dynamic: requires-python
Dynamic: summary
